[
  {
    "modelo": "FIGO",
    "motor": "1.5L",
    "anio": "2016-2018",
    "filtro_aceite": { "marca": "Interfil", "sku": "OF-9566 / OF-3614" },
    "filtro_aceite_sintetico": { "marca": "Interfil", "sku": "OF-9566STX / OF-3614STX" },
    "filtro_aceite_cartucho": { "marca": null, "sku": null },
    "filtro_aire": { "marca": "Interfil", "sku": "F-19A04" },
    "filtro_gasolina": { "marca": "Interfil", "sku": "FGI-356" },
    "filtro_cabina": { "marca": "Interfil", "sku": "CFI-8Z19" }
  },
  {
    "modelo": "FIESTA",
    "motor": "1.0L Turbo",
    "anio": "2014-2015",
    "filtro_aceite": { "marca": "Interfil", "sku": "OF-3614" },
    "filtro_aceite_sintetico": { "marca": "Interfil", "sku": "OF-3614STX" },
    "filtro_aceite_cartucho": { "marca": null, "sku": null },
    "filtro_aire": { "marca": null, "sku": null },
    "filtro_gasolina": { "marca": null, "sku": null },
    "filtro_cabina": { "marca": "Interfil", "sku": "CFI-8Z19" }
  },
  {
    "modelo": "FIESTA",
    "motor": "1.6L",
    "anio": "2009",
    "filtro_aceite": { "marca": "Interfil", "sku": "OF-3614" },
    "filtro_aceite_sintetico": { "marca": "Interfil", "sku": "OF-3614STX" },
    "filtro_aceite_cartucho": { "marca": null, "sku": null },
    "filtro_aire": { "marca": "Interfil", "sku": "F-96A01" },
    "filtro_gasolina": { "marca": "Interfil", "sku": "FGI-283" },
    "filtro_cabina": { "marca": "Interfil", "sku": "CFI-2S6H" }
  },
  {
    "modelo": "FIESTA",
    "motor": "1.6L",
    "anio": "2010-2019",
    "filtro_aceite": { "marca": "Interfil", "sku": "OF-9566 / OF-3614" },
    "filtro_aceite_sintetico": { "marca": "Interfil", "sku": "OF-9566STX / OF-3614STX" },
    "filtro_aceite_cartucho": { "marca": null, "sku": null },
    "filtro_aire": { "marca": "Interfil", "sku": "F-19A04" },
    "filtro_gasolina": { "marca": "Interfil", "sku": "FGI-283" },
    "filtro_cabina": { "marca": "Interfil", "sku": "CFI-8Z19" }
  },
  {
    "modelo": "FIESTA",
    "motor": "1.6L Turbo",
    "anio": "2015-2016",
    "filtro_aceite": { "marca": "Interfil", "sku": "OF-9566 / OF-3614" },
    "filtro_aceite_sintetico": { "marca": "Interfil", "sku": "OF-9566STX / OF-3614STX" },
    "filtro_aceite_cartucho": { "marca": null, "sku": null },
    "filtro_aire": { "marca": "Interfil", "sku": "F-19A04" },
    "filtro_gasolina": { "marca": "Interfil", "sku": "FGI-283" },
    "filtro_cabina": { "marca": "Interfil", "sku": "CFI-1811" }
  },
  {
    "modelo": "FIESTA HATCHBACK",
    "motor": "1.6L",
    "anio": "2003-2007",
    "filtro_aceite": { "marca": "Interfil", "sku": "OF-3600" },
    "filtro_aceite_sintetico": { "marca": "Interfil", "sku": "OF-3600STX" },
    "filtro_aceite_cartucho": { "marca": null, "sku": null },
    "filtro_aire": { "marca": "Interfil", "sku": "F-96A01" },
    "filtro_gasolina": { "marca": "Interfil", "sku": "FGI-133" },
    "filtro_cabina": { "marca": "Interfil", "sku": "CFI-2S6H" }
  },
  {
    "modelo": "FIESTA SEDAN",
    "motor": "1.6L",
    "anio": "2005-2010",
    "filtro_aceite": { "marca": "Interfil", "sku": "OF-3614" },
    "filtro_aceite_sintetico": { "marca": "Interfil", "sku": "OF-3614STX" },
    "filtro_aceite_cartucho": { "marca": null, "sku": null },
    "filtro_aire": { "marca": "Interfil", "sku": "F-96A01" },
    "filtro_gasolina": { "marca": "Interfil", "sku": "FGI-133" },
    "filtro_cabina": { "marca": "Interfil", "sku": "CFI-2S6H" }
  },
  {
    "modelo": "FOCUS",
    "motor": "2.0L",
    "anio": "2000-2004",
    "filtro_aceite": { "marca": "Interfil", "sku": "OF-3600" },
    "filtro_aceite_sintetico": { "marca": "Interfil", "sku": "OF-3600STX" },
    "filtro_aceite_cartucho": { "marca": null, "sku": null },
    "filtro_aire": { "marca": "Interfil", "sku": "F-16A88" },
    "filtro_gasolina": { "marca": "Interfil", "sku": "FGI-133" },
    "filtro_cabina": { "marca": "Interfil", "sku": "CFI-XS4H" }
  },
  {
    "modelo": "FOCUS",
    "motor": "2.0L",
    "anio": "2005-2008",
    "filtro_aceite": { "marca": "Interfil", "sku": "OF-9566" },
    "filtro_aceite_sintetico": { "marca": "Interfil", "sku": "OF-9566STX" },
    "filtro_aceite_cartucho": { "marca": null, "sku": null },
    "filtro_aire": { "marca": "Interfil", "sku": "F-18A90" },
    "filtro_gasolina": { "marca": "Interfil", "sku": "FGI-133" },
    "filtro_cabina": { "marca": "Interfil", "sku": "CFI-1354" }
  },
  {
    "modelo": "FOCUS",
    "motor": "2.0L",
    "anio": "2009-2013",
    "filtro_aceite": { "marca": "Interfil", "sku": "OF-9566" },
    "filtro_aceite_sintetico": { "marca": "Interfil", "sku": "OF-9566STX" },
    "filtro_aceite_cartucho": { "marca": null, "sku": null },
    "filtro_aire": { "marca": "Interfil", "sku": "F-18A90" },
    "filtro_gasolina": { "marca": null, "sku": null },
    "filtro_cabina": { "marca": "Interfil", "sku": "CFI-XS4H" }
  },
  {
    "modelo": "FOCUS",
    "motor": "2.0L",
    "anio": "2014-2016",
    "filtro_aceite": { "marca": "Interfil", "sku": "OF-9566 / OF-3614" },
    "filtro_aceite_sintetico": { "marca": "Interfil", "sku": "OF-9566STX / OF-3614STX" },
    "filtro_aceite_cartucho": { "marca": null, "sku": null },
    "filtro_aire": { "marca": "Interfil", "sku": "F-62A04" },
    "filtro_gasolina": { "marca": null, "sku": null },
    "filtro_cabina": { "marca": "Interfil", "sku": "CFI-6Z19" }
  },
  {
    "modelo": "FOCUS SPORT",
    "motor": "2.0L",
    "anio": "2008-2013",
    "filtro_aceite": { "marca": "Interfil", "sku": "OF-9566" },
    "filtro_aceite_sintetico": { "marca": "Interfil", "sku": "OF-9566STX" },
    "filtro_aceite_cartucho": { "marca": null, "sku": null },
    "filtro_aire": { "marca": "Interfil", "sku": "F-62A04" },
    "filtro_gasolina": { "marca": null, "sku": null },
    "filtro_cabina": { "marca": null, "sku": null }
  },
  {
    "modelo": "FOCUS SPORT",
    "motor": "2.0L Turbo",
    "anio": "2012-2016",
    "filtro_aceite": { "marca": "Interfil", "sku": "OF-3614" },
    "filtro_aceite_sintetico": { "marca": "Interfil", "sku": "OF-3614STX" },
    "filtro_aceite_cartucho": { "marca": null, "sku": null },
    "filtro_aire": { "marca": "Interfil", "sku": "F-62A04" },
    "filtro_gasolina": { "marca": null, "sku": null },
    "filtro_cabina": { "marca": "Interfil", "sku": "CFI-6Z19" }
  },
  {
    "modelo": "FOCUS ST",
    "motor": "2.5L",
    "anio": "2008",
    "filtro_aceite": { "marca": null, "sku": null },
    "filtro_aceite_sintetico": { "marca": null, "sku": null },
    "filtro_aceite_cartucho": { "marca": "Interfil", "sku": "OF-9954" },
    "filtro_aire": { "marca": "Interfil", "sku": "F-71A55" },
    "filtro_gasolina": { "marca": "Interfil", "sku": "FGI-133" },
    "filtro_cabina": { "marca": "Interfil", "sku": "CFI-6Z19" }
  },
  {
    "modelo": "ECOSPORT",
    "motor": "1.0L Turbo",
    "anio": "2019",
    "filtro_aceite": { "marca": "Interfil", "sku": "OF-3614" },
    "filtro_aceite_sintetico": { "marca": "Interfil", "sku": "OF-3614STX" },
    "filtro_aceite_cartucho": { "marca": null, "sku": null },
    "filtro_aire": { "marca": "Interfil", "sku": "F-62A04" },
    "filtro_gasolina": { "marca": null, "sku": null },
    "filtro_cabina": { "marca": "Interfil", "sku": "CFI-8Z19" }
  },
  {
    "modelo": "ECOSPORT",
    "motor": "1.5L",
    "anio": "2018",
    "filtro_aceite": { "marca": "Interfil", "sku": "OF-3614 / OF-7503" },
    "filtro_aceite_sintetico": { "marca": "Interfil", "sku": "OF-3614STX" },
    "filtro_aceite_cartucho": { "marca": null, "sku": null },
    "filtro_aire": { "marca": "Interfil", "sku": "F-15A01" },
    "filtro_gasolina": { "marca": "Interfil", "sku": "FGI-133" },
    "filtro_cabina": { "marca": "Interfil", "sku": "CFI-8Z19" }
  },
  {
    "modelo": "ECOSPORT",
    "motor": "2.0L",
    "anio": "2003-2011",
    "filtro_aceite": { "marca": "Interfil", "sku": "OF-9566" },
    "filtro_aceite_sintetico": { "marca": "Interfil", "sku": "OF-9566STX" },
    "filtro_aceite_cartucho": { "marca": null, "sku": null },
    "filtro_aire": { "marca": "Interfil", "sku": "F-96A21" },
    "filtro_gasolina": { "marca": "Interfil", "sku": "FGI-133" },
    "filtro_cabina": { "marca": "Interfil", "sku": "CFI-2S6H" }
  },
  {
    "modelo": "ECOSPORT",
    "motor": "2.0L",
    "anio": "2012-2017",
    "filtro_aceite": { "marca": "Interfil", "sku": "OF-9566" },
    "filtro_aceite_sintetico": { "marca": "Interfil", "sku": "OF-9566STX" },
    "filtro_aceite_cartucho": { "marca": null, "sku": null },
    "filtro_aire": { "marca": "Interfil", "sku": "F-15A01" },
    "filtro_gasolina": { "marca": null, "sku": null },
    "filtro_cabina": { "marca": "Interfil", "sku": "CFI-8Z19" }
  },
  {
    "modelo": "ECOSPORT",
    "motor": "2.0L",
    "anio": "2018",
    "filtro_aceite": { "marca": "Interfil", "sku": "OF-3614 / OF-7503" },
    "filtro_aceite_sintetico": { "marca": "Interfil", "sku": "OF-3614STX" },
    "filtro_aceite_cartucho": { "marca": null, "sku": null },
    "filtro_aire": { "marca": "Interfil", "sku": "F-15A01" },
    "filtro_gasolina": { "marca": "Interfil", "sku": "FGI-133" },
    "filtro_cabina": { "marca": "Interfil", "sku": "CFI-8Z19" }
  },
  {
    "modelo": "ESCAPE",
    "motor": "1.6L Turbo",
    "anio": "2013-2015",
    "filtro_aceite": { "marca": "Interfil", "sku": "OF-3614" },
    "filtro_aceite_sintetico": { "marca": "Interfil", "sku": "OF-3614STX" },
    "filtro_aceite_cartucho": { "marca": null, "sku": null },
    "filtro_aire": { "marca": "Interfil", "sku": "F-62A04" },
    "filtro_gasolina": { "marca": null, "sku": null },
    "filtro_cabina": { "marca": "Interfil", "sku": "CFI-YL84" }
  },
  {
    "modelo": "ESCAPE",
    "motor": "2.0L",
    "anio": "2001-2004",
    "filtro_aceite": { "marca": "Interfil", "sku": "OF-8316" },
    "filtro_aceite_sintetico": { "marca": null, "sku": null },
    "filtro_aceite_cartucho": { "marca": null, "sku": null },
    "filtro_aire": { "marca": "Interfil", "sku": "F-89A97" },
    "filtro_gasolina": { "marca": "Interfil", "sku": "FGI-11" },
    "filtro_cabina": { "marca": "Interfil", "sku": "CFI-YL84" }
  },
  {
    "modelo": "ESCAPE",
    "motor": "2.0L",
    "anio": "2005",
    "filtro_aceite": { "marca": "Interfil", "sku": "OF-9566" },
    "filtro_aceite_sintetico": { "marca": "Interfil", "sku": "OF-9566STX" },
    "filtro_aceite_cartucho": { "marca": null, "sku": null },
    "filtro_aire": { "marca": "Interfil", "sku": "F-89A97" },
    "filtro_gasolina": { "marca": "Interfil", "sku": "FGI-11" },
    "filtro_cabina": { "marca": "Interfil", "sku": "CFI-YL84" }
  },
  {
    "modelo": "ESCAPE",
    "motor": "2.0L Turbo",
    "anio": "2013-2019",
    "filtro_aceite": { "marca": "Interfil", "sku": "OF-3614" },
    "filtro_aceite_sintetico": { "marca": "Interfil", "sku": "OF-3614STX" },
    "filtro_aceite_cartucho": { "marca": null, "sku": null },
    "filtro_aire": { "marca": "Interfil", "sku": "F-62A04" },
    "filtro_gasolina": { "marca": null, "sku": null },
    "filtro_cabina": { "marca": "Interfil", "sku": "CFI-6Z19" }
  },
  {
    "modelo": "ESCAPE",
    "motor": "2.3L",
    "anio": "2005-2008",
    "filtro_aceite": { "marca": "Interfil", "sku": "OF-9566" },
    "filtro_aceite_sintetico": { "marca": "Interfil", "sku": "OF-9566STX" },
    "filtro_aceite_cartucho": { "marca": null, "sku": null },
    "filtro_aire": { "marca": "Interfil", "sku": "F-89A97" },
    "filtro_gasolina": { "marca": "Interfil", "sku": "FGI-202" },
    "filtro_cabina": { "marca": "Interfil", "sku": "CFI-8L8Z" }
  },
  {
    "modelo": "ESCAPE",
    "motor": "2.5L",
    "anio": "2009-2012",
    "filtro_aceite": { "marca": "Interfil", "sku": "OF-9566 / OF-3614" },
    "filtro_aceite_sintetico": { "marca": "Interfil", "sku": "OF-9566STX / OF-3614STX" },
    "filtro_aceite_cartucho": { "marca": null, "sku": null },
    "filtro_aire": { "marca": "Interfil", "sku": "F-89A97" },
    "filtro_gasolina": { "marca": "Interfil", "sku": "FGI-18" },
    "filtro_cabina": { "marca": "Interfil", "sku": "CFI-8L8Z" }
  },
  {
    "modelo": "ESCAPE",
    "motor": "2.5L",
    "anio": "2013-2019",
    "filtro_aceite": { "marca": "Interfil", "sku": "OF-9566 / OF-3614" },
    "filtro_aceite_sintetico": { "marca": "Interfil", "sku": "OF-9566STX / OF-3614STX" },
    "filtro_aceite_cartucho": { "marca": null, "sku": null },
    "filtro_aire": { "marca": "Interfil", "sku": "F-114A56" },
    "filtro_gasolina": { "marca": "Interfil", "sku": "FGI-18" },
    "filtro_cabina": { "marca": "Interfil", "sku": "CFI-6Z19" }
  },
  {
    "modelo": "ESCAPE",
    "motor": "3.0L V6",
    "anio": "2001-2008",
    "filtro_aceite": { "marca": "Interfil", "sku": "OF-2" },
    "filtro_aceite_sintetico": { "marca": "Interfil", "sku": "OF-2STX" },
    "filtro_aceite_cartucho": { "marca": null, "sku": null },
    "filtro_aire": { "marca": "Interfil", "sku": "F-89A97" },
    "filtro_gasolina": { "marca": "Interfil", "sku": "FGI-11" },
    "filtro_cabina": { "marca": "Interfil", "sku": "CFI-YL84" }
  },
  {
    "modelo": "ESCAPE",
    "motor": "3.0L V6",
    "anio": "2009-2012",
    "filtro_aceite": { "marca": "Interfil", "sku": "OF-10060 / OF-10575" },
    "filtro_aceite_sintetico": { "marca": "Interfil", "sku": "OF-10060STX / OF-10575STX" },
    "filtro_aceite_cartucho": { "marca": null, "sku": null },
    "filtro_aire": { "marca": "Interfil", "sku": "F-9LA84" },
    "filtro_gasolina": { "marca": "Interfil", "sku": "FGI-18" },
    "filtro_cabina": { "marca": "Interfil", "sku": "CFI-8L8Z" }
  },
  {
    "modelo": "EDGE",
    "motor": "2.0L",
    "anio": "2012-2015",
    "filtro_aceite": { "marca": "Interfil", "sku": "OF-3614" },
    "filtro_aceite_sintetico": { "marca": "Interfil", "sku": "OF-3614STX" },
    "filtro_aceite_cartucho": { "marca": null, "sku": null },
    "filtro_aire": { "marca": "Interfil", "sku": "F-102A42" },
    "filtro_gasolina": { "marca": null, "sku": null },
    "filtro_cabina": { "marca": "Interfil", "sku": "CFI-10547" }
  },
  {
    "modelo": "EDGE",
    "motor": "2.0L Turbo",
    "anio": "2017-2020",
    "filtro_aceite": { "marca": "Interfil", "sku": "OF-3614" },
    "filtro_aceite_sintetico": { "marca": "Interfil", "sku": "OF-3614STX" },
    "filtro_aceite_cartucho": { "marca": null, "sku": null },
    "filtro_aire": { "marca": "Interfil", "sku": "F-114A80" },
    "filtro_gasolina": { "marca": "Interfil", "sku": "FGI-238" },
    "filtro_cabina": { "marca": "Interfil", "sku": "CFI-9Z19" }
  },
  {
    "modelo": "EDGE",
    "motor": "2.7L Turbo V6",
    "anio": "2016-2020",
    "filtro_aceite": { "marca": null, "sku": null },
    "filtro_aceite_sintetico": { "marca": null, "sku": null },
    "filtro_aceite_cartucho": { "marca": null, "sku": null },
    "filtro_aire": { "marca": "Interfil", "sku": "F-114A80" },
    "filtro_gasolina": { "marca": "Interfil", "sku": "FGI-238" },
    "filtro_cabina": { "marca": "Interfil", "sku": "CFI-9Z19" }
  },
  {
    "modelo": "EDGE",
    "motor": "3.5L V6",
    "anio": "2007-2015",
    "filtro_aceite": { "marca": "Interfil", "sku": "OF-3600" },
    "filtro_aceite_sintetico": { "marca": "Interfil", "sku": "OF-3600STX" },
    "filtro_aceite_cartucho": { "marca": null, "sku": null },
    "filtro_aire": { "marca": "Interfil", "sku": "F-102A42" },
    "filtro_gasolina": { "marca": null, "sku": null },
    "filtro_cabina": { "marca": "Interfil", "sku": "CFI-10547" }
  },
  {
    "modelo": "EDGE",
    "motor": "3.5L V6",
    "anio": "2016",
    "filtro_aceite": { "marca": "Interfil", "sku": "OF-10060 / OF-10575" },
    "filtro_aceite_sintetico": { "marca": "Interfil", "sku": "OF-10060STX / OF-10575STX" },
    "filtro_aceite_cartucho": { "marca": null, "sku": null },
    "filtro_aire": { "marca": "Interfil", "sku": "F-114A80" },
    "filtro_gasolina": { "marca": "Interfil", "sku": "FGI-238" },
    "filtro_cabina": { "marca": "Interfil", "sku": "CFI-10547" }
  },
  {
    "modelo": "EDGE",
    "motor": "3.7L V6",
    "anio": "2011-2015",
    "filtro_aceite": { "marca": "Interfil", "sku": "OF-10060 / OF-10575" },
    "filtro_aceite_sintetico": { "marca": "Interfil", "sku": "OF-10060STX / OF-10575STX" },
    "filtro_aceite_cartucho": { "marca": null, "sku": null },
    "filtro_aire": { "marca": "Interfil", "sku": "F-102A42" },
    "filtro_gasolina": { "marca": null, "sku": null },
    "filtro_cabina": { "marca": "Interfil", "sku": "CFI-10547" }
  },
  {
    "modelo": "FUSION",
    "motor": "1.5L",
    "anio": "2014-2020",
    "filtro_aceite": { "marca": "Interfil", "sku": "OF-3614" },
    "filtro_aceite_sintetico": { "marca": "Interfil", "sku": "OF-3614STX" },
    "filtro_aceite_cartucho": { "marca": null, "sku": null },
    "filtro_aire": { "marca": "Interfil", "sku": "F-114A80" },
    "filtro_gasolina": { "marca": null, "sku": null },
    "filtro_cabina": { "marca": null, "sku": null }
  },
  {
    "modelo": "FUSION",
    "motor": "1.6L Turbo",
    "anio": "2013-2017",
    "filtro_aceite": { "marca": "Interfil", "sku": "OF-3614" },
    "filtro_aceite_sintetico": { "marca": "Interfil", "sku": "OF-3614STX" },
    "filtro_aceite_cartucho": { "marca": null, "sku": null },
    "filtro_aire": { "marca": "Interfil", "sku": "F-114A80" },
    "filtro_gasolina": { "marca": null, "sku": null },
    "filtro_cabina": { "marca": "Interfil", "sku": "CFI-9Z19" }
  },
  {
    "modelo": "FUSION",
    "motor": "2.0L Turbo",
    "anio": "2013-2020",
    "filtro_aceite": { "marca": "Interfil", "sku": "OF-9566 / OF-3614" },
    "filtro_aceite_sintetico": { "marca": "Interfil", "sku": "OF-9566STX / OF-3614STX" },
    "filtro_aceite_cartucho": { "marca": null, "sku": null },
    "filtro_aire": { "marca": "Interfil", "sku": "F-114A80" },
    "filtro_gasolina": { "marca": null, "sku": null },
    "filtro_cabina": { "marca": "Interfil", "sku": "CFI-9Z19" }
  },
  {
    "modelo": "FUSION",
    "motor": "2.3L",
    "anio": "2006-2009",
    "filtro_aceite": { "marca": "Interfil", "sku": "OF-9641 / OF-3614" },
    "filtro_aceite_sintetico": { "marca": "Interfil", "sku": "OF-9566STX" },
    "filtro_aceite_cartucho": { "marca": null, "sku": null },
    "filtro_aire": { "marca": "Interfil", "sku": "F-100A94" },
    "filtro_gasolina": { "marca": null, "sku": null },
    "filtro_cabina": { "marca": null, "sku": null }
  },
  {
    "modelo": "FUSION",
    "motor": "2.5L",
    "anio": "2010-2012",
    "filtro_aceite": { "marca": "Interfil", "sku": "OF-9566 / OF-3614" },
    "filtro_aceite_sintetico": { "marca": "Interfil", "sku": "OF-9566STX / OF-3614STX" },
    "filtro_aceite_cartucho": { "marca": null, "sku": null },
    "filtro_aire": { "marca": "Interfil", "sku": "F-100A94" },
    "filtro_gasolina": { "marca": null, "sku": null },
    "filtro_cabina": { "marca": null, "sku": null }
  },
  {
    "modelo": "FUSION",
    "motor": "2.5L",
    "anio": "2013-2020",
    "filtro_aceite": { "marca": "Interfil", "sku": "OF-9566 / OF-3614" },
    "filtro_aceite_sintetico": { "marca": "Interfil", "sku": "OF-9566STX / OF-3614STX" },
    "filtro_aceite_cartucho": { "marca": null, "sku": null },
    "filtro_aire": { "marca": "Interfil", "sku": "F-114A80" },
    "filtro_gasolina": { "marca": null, "sku": null },
    "filtro_cabina": { "marca": "Interfil", "sku": "CFI-9Z19" }
  },
  {
    "modelo": "FUSION",
    "motor": "3.0L V6",
    "anio": "2006-2007",
    "filtro_aceite": { "marca": "Interfil", "sku": "OF-2" },
    "filtro_aceite_sintetico": { "marca": "Interfil", "sku": "OF-2STX" },
    "filtro_aceite_cartucho": { "marca": null, "sku": null },
    "filtro_aire": { "marca": "Interfil", "sku": "F-6EA53" },
    "filtro_gasolina": { "marca": null, "sku": null },
    "filtro_cabina": { "marca": null, "sku": null }
  },
  {
    "modelo": "FUSION",
    "motor": "3.0L V6",
    "anio": "2008-2012",
    "filtro_aceite": { "marca": "Interfil", "sku": "OF-10060 / OF-10575" },
    "filtro_aceite_sintetico": { "marca": "Interfil", "sku": "OF-10060STX / OF-10575STX" },
    "filtro_aceite_cartucho": { "marca": null, "sku": null },
    "filtro_aire": { "marca": "Interfil", "sku": "F-6EA53" },
    "filtro_gasolina": { "marca": null, "sku": null },
    "filtro_cabina": { "marca": null, "sku": null }
  },
  {
    "modelo": "FUSION HIBRIDO",
    "motor": "2.0L",
    "anio": "2013-2014",
    "filtro_aceite": { "marca": "Interfil", "sku": "OF-9566 / OF-3614" },
    "filtro_aceite_sintetico": { "marca": "Interfil", "sku": "OF-9566STX / OF-3614STX" },
    "filtro_aceite_cartucho": { "marca": null, "sku": null },
    "filtro_aire": { "marca": null, "sku": null },
    "filtro_gasolina": { "marca": null, "sku": null },
    "filtro_cabina": { "marca": null, "sku": null }
  },
  {
    "modelo": "EXPLORER",
    "motor": "2.0L Turbo",
    "anio": "2012-2015",
    "filtro_aceite": { "marca": "Interfil", "sku": "OF-3614" },
    "filtro_aceite_sintetico": { "marca": "Interfil", "sku": "OF-3614STX" },
    "filtro_aceite_cartucho": { "marca": null, "sku": null },
    "filtro_aire": { "marca": "Interfil", "sku": "F-102A42" },
    "filtro_gasolina": { "marca": null, "sku": null },
    "filtro_cabina": { "marca": "Interfil", "sku": "CFI-11176" }
  },
  {
    "modelo": "EXPLORER",
    "motor": "3.5L V6",
    "anio": "2011-2019",
    "filtro_aceite": { "marca": "Interfil", "sku": "OF-10060 / OF-10575" },
    "filtro_aceite_sintetico": { "marca": "Interfil", "sku": "OF-10060STX / OF-10575STX" },
    "filtro_aceite_cartucho": { "marca": null, "sku": null },
    "filtro_aire": { "marca": "Interfil", "sku": "F-102A42" },
    "filtro_gasolina": { "marca": null, "sku": null },
    "filtro_cabina": { "marca": "Interfil", "sku": "CFI-11176" }
  },
  {
    "modelo": "EXPLORER",
    "motor": "4.0L V6",
    "anio": "1991-2000",
    "filtro_aceite": { "marca": "Interfil", "sku": "OF-8" },
    "filtro_aceite_sintetico": { "marca": null, "sku": null },
    "filtro_aceite_cartucho": { "marca": null, "sku": null },
    "filtro_aire": { "marca": "Interfil", "sku": "F-50A58 / F-77A74 / F-82A43" },
    "filtro_gasolina": { "marca": "Interfil", "sku": "FGI-18" },
    "filtro_cabina": { "marca": null, "sku": null }
  },
  {
    "modelo": "EXPLORER",
    "motor": "4.0L V6",
    "anio": "2001-2010",
    "filtro_aceite": { "marca": "Interfil", "sku": "OF-2" },
    "filtro_aceite_sintetico": { "marca": "Interfil", "sku": "OF-2STX" },
    "filtro_aceite_cartucho": { "marca": null, "sku": null },
    "filtro_aire": { "marca": "Interfil", "sku": "F-82A43 / F-93A32" },
    "filtro_gasolina": { "marca": "Interfil", "sku": "FGI-238" },
    "filtro_cabina": { "marca": null, "sku": null }
  },
  {
    "modelo": "EXPLORER",
    "motor": "4.6L V8",
    "anio": "2001-2010",
    "filtro_aceite": { "marca": "Interfil", "sku": "OF-2" },
    "filtro_aceite_sintetico": { "marca": "Interfil", "sku": "OF-2STX" },
    "filtro_aceite_cartucho": { "marca": null, "sku": null },
    "filtro_aire": { "marca": "Interfil", "sku": "F-82A43 / F-93A32 / F-101A73" },
    "filtro_gasolina": { "marca": "Interfil", "sku": "FGI-238" },
    "filtro_cabina": { "marca": null, "sku": null }
  },
  {
    "modelo": "EXPLORER HIBRIDO",
    "motor": "3.3L V6",
    "anio": "2020",
    "filtro_aceite": { "marca": "Interfil", "sku": "OF-10575" },
    "filtro_aceite_sintetico": { "marca": "Interfil", "sku": "OF-10575STX" },
    "filtro_aceite_cartucho": { "marca": null, "sku": null },
    "filtro_aire": { "marca": "Interfil", "sku": "F-109A10" },
    "filtro_gasolina": { "marca": null, "sku": null },
    "filtro_cabina": { "marca": null, "sku": null }
  },
  {
    "modelo": "EXPEDITION",
    "motor": "3.5L Turbo V6",
    "anio": "2015-2020",
    "filtro_aceite": { "marca": "Interfil", "sku": "OF-10060 / OF-10575" },
    "filtro_aceite_sintetico": { "marca": "Interfil", "sku": "OF-10060STX / OF-10575STX" },
    "filtro_aceite_cartucho": { "marca": null, "sku": null },
    "filtro_aire": { "marca": "Interfil", "sku": "F-18A83" },
    "filtro_gasolina": { "marca": "Interfil", "sku": "FGI-207A" },
    "filtro_cabina": { "marca": "Interfil", "sku": "CFI-12150" }
  },
  {
    "modelo": "EXPEDITION",
    "motor": "4.6L V8",
    "anio": "1997-2007",
    "filtro_aceite": { "marca": "Interfil", "sku": "OF-2" },
    "filtro_aceite_sintetico": { "marca": "Interfil", "sku": "OF-2STX" },
    "filtro_aceite_cartucho": { "marca": null, "sku": null },
    "filtro_aire": { "marca": "Interfil", "sku": "F-80A04 / F-96A87" },
    "filtro_gasolina": { "marca": "Interfil", "sku": "FGI-133" },
    "filtro_cabina": { "marca": "Interfil", "sku": "CFI-19N6" }
  },
  {
    "modelo": "EXPEDITION",
    "motor": "5.4L V8",
    "anio": "1997-2014",
    "filtro_aceite": { "marca": "Interfil", "sku": "OF-2" },
    "filtro_aceite_sintetico": { "marca": "Interfil", "sku": "OF-2STX" },
    "filtro_aceite_cartucho": { "marca": null, "sku": null },
    "filtro_aire": { "marca": "Interfil", "sku": "F-80A04 / F-18A83" },
    "filtro_gasolina": { "marca": "Interfil", "sku": "FGI-207A" },
    "filtro_cabina": { "marca": "Interfil", "sku": "CFI-19N6" }
  },
  {
    "modelo": "RANGER",
    "motor": "2.0L Turbo Diesel",
    "anio": "2012-2015",
    "filtro_aceite": { "marca": "Interfil", "sku": "OF-1720" },
    "filtro_aceite_sintetico": { "marca": null, "sku": null },
    "filtro_aceite_cartucho": { "marca": null, "sku": null },
    "filtro_aire": { "marca": "Interfil", "sku": "F-35A96" },
    "filtro_gasolina": { "marca": null, "sku": null },
    "filtro_cabina": { "marca": null, "sku": null }
  },
  {
    "modelo": "RANGER",
    "motor": "2.2L Turbo Diesel",
    "anio": "2016-2018",
    "filtro_aceite": { "marca": "Interfil", "sku": "OF-1720" },
    "filtro_aceite_sintetico": { "marca": null, "sku": null },
    "filtro_aceite_cartucho": { "marca": null, "sku": null },
    "filtro_aire": { "marca": "Interfil", "sku": "F-35A96" },
    "filtro_gasolina": { "marca": null, "sku": null },
    "filtro_cabina": { "marca": "Interfil", "sku": "CFI-1354" }
  },
  {
    "modelo": "RANGER",
    "motor": "2.3L",
    "anio": "2001-2004",
    "filtro_aceite": { "marca": "Interfil", "sku": "OF-3600 / OF-9566" },
    "filtro_aceite_sintetico": { "marca": "Interfil", "sku": "OF-3600STX / OF-9566STX" },
    "filtro_aceite_cartucho": { "marca": null, "sku": null },
    "filtro_aire": { "marca": "Interfil", "sku": "F-82A43" },
    "filtro_gasolina": { "marca": "Interfil", "sku": "FGI-203A" },
    "filtro_cabina": { "marca": null, "sku": null }
  },
  {
    "modelo": "RANGER",
    "motor": "2.3L",
    "anio": "2005-2012",
    "filtro_aceite": { "marca": "Interfil", "sku": "OF-9566" },
    "filtro_aceite_sintetico": { "marca": "Interfil", "sku": "OF-9566STX" },
    "filtro_aceite_cartucho": { "marca": null, "sku": null },
    "filtro_aire": { "marca": "Interfil", "sku": "F-82A43" },
    "filtro_gasolina": { "marca": "Interfil", "sku": "FGI-207A" },
    "filtro_cabina": { "marca": null, "sku": null }
  },
  {
    "modelo": "RANGER",
    "motor": "2.5L",
    "anio": "2015-2020",
    "filtro_aceite": { "marca": "Interfil", "sku": "OF-2 / OF-10060" },
    "filtro_aceite_sintetico": { "marca": "Interfil", "sku": "OF-2STX / OF-10060STX" },
    "filtro_aceite_cartucho": { "marca": null, "sku": null },
    "filtro_aire": { "marca": "Interfil", "sku": "F-35A96" },
    "filtro_gasolina": { "marca": "Interfil", "sku": "FGI-348" },
    "filtro_cabina": { "marca": "Interfil", "sku": "CFI-1354" }
  },
  {
    "modelo": "RANGER",
    "motor": "3.0L V6",
    "anio": "2001-2009",
    "filtro_aceite": { "marca": "Interfil", "sku": "OF-3600" },
    "filtro_aceite_sintetico": { "marca": "Interfil", "sku": "OF-3600STX" },
    "filtro_aceite_cartucho": { "marca": null, "sku": null },
    "filtro_aire": { "marca": "Interfil", "sku": "F-82A43 / F-95A63" },
    "filtro_gasolina": { "marca": "Interfil", "sku": "FGI-203A / FGI-207A" },
    "filtro_cabina": { "marca": null, "sku": null }
  },
  {
    "modelo": "RANGER",
    "motor": "4.0L V6",
    "anio": "2001-2012",
    "filtro_aceite": { "marca": "Interfil", "sku": "OF-2" },
    "filtro_aceite_sintetico": { "marca": "Interfil", "sku": "OF-2STX" },
    "filtro_aceite_cartucho": { "marca": null, "sku": null },
    "filtro_aire": { "marca": "Interfil", "sku": "F-82A43 / F-95A63" },
    "filtro_gasolina": { "marca": "Interfil", "sku": "FGI-207A" },
    "filtro_cabina": { "marca": null, "sku": null }
  },
  {
    "modelo": "LOBO",
    "motor": "4.6L V8",
    "anio": "1997-2007",
    "filtro_aceite": { "marca": "Interfil", "sku": "OF-2" },
    "filtro_aceite_sintetico": { "marca": "Interfil", "sku": "OF-2STX" },
    "filtro_aceite_cartucho": { "marca": null, "sku": null },
    "filtro_aire": { "marca": "Interfil", "sku": "F-80A04" },
    "filtro_gasolina": { "marca": "Interfil", "sku": "FGI-133" },
    "filtro_cabina": { "marca": "Interfil", "sku": "CFI-19N6" }
  },
  {
    "modelo": "LOBO",
    "motor": "5.4L V8",
    "anio": "2000-2007",
    "filtro_aceite": { "marca": "Interfil", "sku": "OF-2" },
    "filtro_aceite_sintetico": { "marca": "Interfil", "sku": "OF-2STX" },
    "filtro_aceite_cartucho": { "marca": null, "sku": null },
    "filtro_aire": { "marca": "Interfil", "sku": "F-80A04 / F-96A87" },
    "filtro_gasolina": { "marca": "Interfil", "sku": "FGI-238" },
    "filtro_cabina": { "marca": "Interfil", "sku": "CFI-19N6" }
  },
  {
    "modelo": "F-150",
    "motor": "3.5L Turbo V6",
    "anio": "2011-2017",
    "filtro_aceite": { "marca": "Interfil", "sku": "OF-10060 / OF-10575" },
    "filtro_aceite_sintetico": { "marca": "Interfil", "sku": "OF-10060STX / OF-10575STX" },
    "filtro_aceite_cartucho": { "marca": null, "sku": null },
    "filtro_aire": { "marca": "Interfil", "sku": "F-18A83" },
    "filtro_gasolina": { "marca": null, "sku": null },
    "filtro_cabina": { "marca": "Interfil", "sku": "CFI-12150" }
  },
  {
    "modelo": "F-150",
    "motor": "4.2L V6",
    "anio": "1997-2008",
    "filtro_aceite": { "marca": "Interfil", "sku": "OF-3600" },
    "filtro_aceite_sintetico": { "marca": "Interfil", "sku": "OF-3600STX" },
    "filtro_aceite_cartucho": { "marca": null, "sku": null },
    "filtro_aire": { "marca": "Interfil", "sku": "F-80A04" },
    "filtro_gasolina": { "marca": "Interfil", "sku": "FGI-18 / FGI-238" },
    "filtro_cabina": { "marca": "Interfil", "sku": "CFI-19N6" }
  },
  {
    "modelo": "F-150",
    "motor": "4.6L V8",
    "anio": "1997-2010",
    "filtro_aceite": { "marca": "Interfil", "sku": "OF-2" },
    "filtro_aceite_sintetico": { "marca": "Interfil", "sku": "OF-2STX" },
    "filtro_aceite_cartucho": { "marca": null, "sku": null },
    "filtro_aire": { "marca": "Interfil", "sku": "F-80A04 / F-18A83" },
    "filtro_gasolina": { "marca": "Interfil", "sku": "FGI-18 / FGI-133 / FGI-238" },
    "filtro_cabina": { "marca": "Interfil", "sku": "CFI-19N6" }
  },
  {
    "modelo": "F-150",
    "motor": "5.0L V8",
    "anio": "2011-2020",
    "filtro_aceite": { "marca": "Interfil", "sku": "OF-10060 / OF-10575" },
    "filtro_aceite_sintetico": { "marca": "Interfil", "sku": "OF-10060STX / OF-10575STX" },
    "filtro_aceite_cartucho": { "marca": null, "sku": null },
    "filtro_aire": { "marca": "Interfil", "sku": "F-18A83" },
    "filtro_gasolina": { "marca": null, "sku": null },
    "filtro_cabina": { "marca": "Interfil", "sku": "CFI-12150" }
  },
  {
    "modelo": "F-150",
    "motor": "5.4L V8",
    "anio": "1997-2010",
    "filtro_aceite": { "marca": "Interfil", "sku": "OF-2" },
    "filtro_aceite_sintetico": { "marca": "Interfil", "sku": "OF-2STX" },
    "filtro_aceite_cartucho": { "marca": null, "sku": null },
    "filtro_aire": { "marca": "Interfil", "sku": "F-80A04 / F-96A87 / F-18A83" },
    "filtro_gasolina": { "marca": "Interfil", "sku": "FGI-18 / FGI-133 / FGI-238" },
    "filtro_cabina": { "marca": "Interfil", "sku": "CFI-19N6 / CFI-12150" }
  },
  {
    "modelo": "F-150",
    "motor": "6.2L V8",
    "anio": "2010-2016",
    "filtro_aceite": { "marca": "Interfil", "sku": "OF-2" },
    "filtro_aceite_sintetico": { "marca": "Interfil", "sku": "OF-2STX" },
    "filtro_aceite_cartucho": { "marca": null, "sku": null },
    "filtro_aire": { "marca": "Interfil", "sku": "F-18A83" },
    "filtro_gasolina": { "marca": "Interfil", "sku": "FGI-238" },
    "filtro_cabina": { "marca": "Interfil", "sku": "CFI-12150" }
  },
  {
    "modelo": "F-150",
    "motor": "6.7L Turbo Diesel V8",
    "anio": "2011-2019",
    "filtro_aceite": { "marca": "Interfil", "sku": "OF-10890" },
    "filtro_aceite_sintetico": { "marca": "Interfil", "sku": "OF-10890STX" },
    "filtro_aceite_cartucho": { "marca": null, "sku": null },
    "filtro_aire": { "marca": "Interfil", "sku": "F-108A88" },
    "filtro_gasolina": { "marca": "Interfil", "sku": "FGI-339D" },
    "filtro_cabina": { "marca": "Interfil", "sku": "CFI-12150" }
  },
  {
    "modelo": "MUSTANG",
    "motor": "2.3L",
    "anio": "2015-2020",
    "filtro_aceite": { "marca": "Interfil", "sku": "OF-9566 / OF-3614" },
    "filtro_aceite_sintetico": { "marca": "Interfil", "sku": "OF-9566STX / OF-3614STX" },
    "filtro_aceite_cartucho": { "marca": null, "sku": null },
    "filtro_aire": { "marca": "Interfil", "sku": "F-19A18" },
    "filtro_gasolina": { "marca": null, "sku": null },
    "filtro_cabina": { "marca": "Interfil", "sku": "CFI-10195" }
  },
  {
    "modelo": "MUSTANG",
    "motor": "2.3L Turbo",
    "anio": "2018-2020",
    "filtro_aceite": { "marca": "Interfil", "sku": "OF-10060 / OF-10575" },
    "filtro_aceite_sintetico": { "marca": "Interfil", "sku": "OF-10060STX / OF-10575STX" },
    "filtro_aceite_cartucho": { "marca": null, "sku": null },
    "filtro_aire": { "marca": "Interfil", "sku": "F-19A18" },
    "filtro_gasolina": { "marca": null, "sku": null },
    "filtro_cabina": { "marca": "Interfil", "sku": "CFI-10195" }
  },
  {
    "modelo": "MUSTANG",
    "motor": "3.7L V6",
    "anio": "2011-2017",
    "filtro_aceite": { "marca": "Interfil", "sku": "OF-10060 / OF-10575" },
    "filtro_aceite_sintetico": { "marca": "Interfil", "sku": "OF-10060STX / OF-10575STX" },
    "filtro_aceite_cartucho": { "marca": null, "sku": null },
    "filtro_aire": { "marca": "Interfil", "sku": "F-107A81 / F-19A18" },
    "filtro_gasolina": { "marca": null, "sku": null },
    "filtro_cabina": { "marca": "Interfil", "sku": "CFI-10370 / CFI-10195" }
  },
  {
    "modelo": "MUSTANG",
    "motor": "3.8L V6",
    "anio": "1994-2004",
    "filtro_aceite": { "marca": "Interfil", "sku": "OF-3600" },
    "filtro_aceite_sintetico": { "marca": "Interfil", "sku": "OF-3600STX" },
    "filtro_aceite_cartucho": { "marca": null, "sku": null },
    "filtro_aire": { "marca": "Interfil", "sku": "F-77A30" },
    "filtro_gasolina": { "marca": "Interfil", "sku": "FGI-11 / FGI-133" },
    "filtro_cabina": { "marca": null, "sku": null }
  },
  {
    "modelo": "MUSTANG",
    "motor": "4.0L V6",
    "anio": "2005-2010",
    "filtro_aceite": { "marca": "Interfil", "sku": "OF-2" },
    "filtro_aceite_sintetico": { "marca": "Interfil", "sku": "OF-2STX" },
    "filtro_aceite_cartucho": { "marca": null, "sku": null },
    "filtro_aire": { "marca": "Interfil", "sku": "F-98A95" },
    "filtro_gasolina": { "marca": "Interfil", "sku": "FGI-238" },
    "filtro_cabina": { "marca": "Interfil", "sku": "CFI-10370" }
  },
  {
    "modelo": "MUSTANG",
    "motor": "4.6L V8",
    "anio": "1996-2009",
    "filtro_aceite": { "marca": "Interfil", "sku": "OF-2" },
    "filtro_aceite_sintetico": { "marca": "Interfil", "sku": "OF-2STX" },
    "filtro_aceite_cartucho": { "marca": null, "sku": null },
    "filtro_aire": { "marca": "Interfil", "sku": "F-80A04 / F-98A95" },
    "filtro_gasolina": { "marca": "Interfil", "sku": "FGI-11 / FGI-133 / FGI-238" },
    "filtro_cabina": { "marca": "Interfil", "sku": "CFI-10370" }
  },
  {
    "modelo": "MUSTANG",
    "motor": "5.0L V8",
    "anio": "2011-2020",
    "filtro_aceite": { "marca": "Interfil", "sku": "OF-10060 / OF-10575" },
    "filtro_aceite_sintetico": { "marca": "Interfil", "sku": "OF-10060STX / OF-10575STX" },
    "filtro_aceite_cartucho": { "marca": null, "sku": null },
    "filtro_aire": { "marca": "Interfil", "sku": "F-107A81 / F-19A18" },
    "filtro_gasolina": { "marca": null, "sku": null },
    "filtro_cabina": { "marca": "Interfil", "sku": "CFI-10370 / CFI-10195" }
  },
  {
    "modelo": "MUSTANG",
    "motor": "5.4L V8",
    "anio": "2007-2014",
    "filtro_aceite": { "marca": "Interfil", "sku": "OF-2 / OF-6714" },
    "filtro_aceite_sintetico": { "marca": "Interfil", "sku": "OF-2STX" },
    "filtro_aceite_cartucho": { "marca": null, "sku": null },
    "filtro_aire": { "marca": "Interfil", "sku": "F-32A96" },
    "filtro_gasolina": { "marca": "Interfil", "sku": "FGI-238" },
    "filtro_cabina": { "marca": "Interfil", "sku": "CFI-10370" }
  },
  {
    "modelo": "MUSTANG",
    "motor": "5.8L V8",
    "anio": "2013-2014",
    "filtro_aceite": { "marca": "Interfil", "sku": "OF-2" },
    "filtro_aceite_sintetico": { "marca": "Interfil", "sku": "OF-2STX" },
    "filtro_aceite_cartucho": { "marca": null, "sku": null },
    "filtro_aire": { "marca": null, "sku": null },
    "filtro_gasolina": { "marca": "Interfil", "sku": "FGI-238" },
    "filtro_cabina": { "marca": "Interfil", "sku": "CFI-10370" }
  },
  {
    "modelo": "TRANSIT",
    "motor": "2.2L Turbo Diesel",
    "anio": "2009-2011",
    "filtro_aceite": { "marca": null, "sku": null },
    "filtro_aceite_sintetico": { "marca": null, "sku": null },
    "filtro_aceite_cartucho": { "marca": "Interfil", "sku": "OF-6C67" },
    "filtro_aire": { "marca": "Interfil", "sku": "F-6CA11" },
    "filtro_gasolina": { "marca": null, "sku": null },
    "filtro_cabina": { "marca": null, "sku": null }
  },
  {
    "modelo": "TRANSIT",
    "motor": "2.2L Turbo Diesel",
    "anio": "2012-2017",
    "filtro_aceite": { "marca": "Interfil", "sku": "OF-2Q67" },
    "filtro_aceite_sintetico": { "marca": null, "sku": null },
    "filtro_aceite_cartucho": { "marca": null, "sku": null },
    "filtro_aire": { "marca": "Interfil", "sku": "F-11A96" },
    "filtro_gasolina": { "marca": "Interfil", "sku": "FGI-334D" },
    "filtro_cabina": { "marca": "Interfil", "sku": "CFI-1812" }
  },
  {
    "modelo": "TRANSIT",
    "motor": "3.7L V6",
    "anio": "2015-2019",
    "filtro_aceite": { "marca": "Interfil", "sku": "OF-10060 / OF-10575" },
    "filtro_aceite_sintetico": { "marca": "Interfil", "sku": "OF-10060STX / OF-10575STX" },
    "filtro_aceite_cartucho": { "marca": null, "sku": null },
    "filtro_aire": { "marca": "Interfil", "sku": "F-103A16" },
    "filtro_gasolina": { "marca": null, "sku": null },
    "filtro_cabina": { "marca": null, "sku": null }
  },
  {
    "modelo": "TRANSIT CONNECT",
    "motor": "1.6L Turbo",
    "anio": "2014-2015",
    "filtro_aceite": { "marca": "Interfil", "sku": "OF-9566" },
    "filtro_aceite_sintetico": { "marca": "Interfil", "sku": "OF-9566STX" },
    "filtro_aceite_cartucho": { "marca": null, "sku": null },
    "filtro_aire": { "marca": "Interfil", "sku": "F-62A04" },
    "filtro_gasolina": { "marca": null, "sku": null },
    "filtro_cabina": { "marca": "Interfil", "sku": "CFI-6Z19" }
  },
  {
    "modelo": "TRANSIT CONNECT",
    "motor": "2.0L",
    "anio": "2010-2013",
    "filtro_aceite": { "marca": "Interfil", "sku": "OF-9566" },
    "filtro_aceite_sintetico": { "marca": "Interfil", "sku": "OF-9566STX" },
    "filtro_aceite_cartucho": { "marca": null, "sku": null },
    "filtro_aire": { "marca": null, "sku": null },
    "filtro_gasolina": { "marca": null, "sku": null },
    "filtro_cabina": { "marca": "Interfil", "sku": "CFI-XS4H" }
  },
  {
    "modelo": "TRANSIT CONNECT",
    "motor": "2.5L",
    "anio": "2014-2015",
    "filtro_aceite": { "marca": "Interfil", "sku": "OF-9566" },
    "filtro_aceite_sintetico": { "marca": "Interfil", "sku": "OF-9566STX" },
    "filtro_aceite_cartucho": { "marca": null, "sku": null },
    "filtro_aire": { "marca": "Interfil", "sku": "F-114A80" },
    "filtro_gasolina": { "marca": null, "sku": null },
    "filtro_cabina": { "marca": "Interfil", "sku": "CFI-6Z19" }
  },
  {
    "modelo": "C-MAX HIBRIDO",
    "motor": "2.0L",
    "anio": "2013-2019",
    "filtro_aceite": { "marca": "Interfil", "sku": "OF-3614" },
    "filtro_aceite_sintetico": { "marca": "Interfil", "sku": "OF-3614STX" },
    "filtro_aceite_cartucho": { "marca": null, "sku": null },
    "filtro_aire": { "marca": null, "sku": null },
    "filtro_gasolina": { "marca": null, "sku": null },
    "filtro_cabina": { "marca": null, "sku": null }
  },
  {
    "modelo": "KA",
    "motor": "1.6L",
    "anio": "2001-2007",
    "filtro_aceite": { "marca": "Interfil", "sku": "OF-8316" },
    "filtro_aceite_sintetico": { "marca": null, "sku": null },
    "filtro_aceite_cartucho": { "marca": null, "sku": null },
    "filtro_aire": { "marca": "Interfil", "sku": "F-87A36" },
    "filtro_gasolina": { "marca": "Interfil", "sku": "FGI-133" },
    "filtro_cabina": { "marca": "Interfil", "sku": "CFI-96FW" }
  },
  {
    "modelo": "IKON",
    "motor": "1.6L",
    "anio": "2000-2015",
    "filtro_aceite": { "marca": "Interfil", "sku": "OF-3600" },
    "filtro_aceite_sintetico": { "marca": "Interfil", "sku": "OF-3600STX" },
    "filtro_aceite_cartucho": { "marca": null, "sku": null },
    "filtro_aire": { "marca": "Interfil", "sku": "F-580A" },
    "filtro_gasolina": { "marca": "Interfil", "sku": "FGI-132" },
    "filtro_cabina": { "marca": null, "sku": null }
  },
  {
    "modelo": "COURIER",
    "motor": "1.6L",
    "anio": "2001-2007",
    "filtro_aceite": { "marca": "Interfil", "sku": "OF-3600" },
    "filtro_aceite_sintetico": { "marca": "Interfil", "sku": "OF-3600STX" },
    "filtro_aceite_cartucho": { "marca": null, "sku": null },
    "filtro_aire": { "marca": "Interfil", "sku": "F-580A" },
    "filtro_gasolina": { "marca": "Interfil", "sku": "FGI-18" },
    "filtro_cabina": { "marca": "Interfil", "sku": "CFI-96FW" }
  },
  {
    "modelo": "COURIER L/XL",
    "motor": "1.6L",
    "anio": "2003-2006",
    "filtro_aceite": { "marca": "Interfil", "sku": "OF-8316" },
    "filtro_aceite_sintetico": { "marca": null, "sku": null },
    "filtro_aceite_cartucho": { "marca": null, "sku": null },
    "filtro_aire": { "marca": "Interfil", "sku": "F-580A" },
    "filtro_gasolina": { "marca": "Interfil", "sku": "FGI-132" },
    "filtro_cabina": { "marca": "Interfil", "sku": "CFI-96FW" }
  },
  {
    "modelo": "MONDEO",
    "motor": "2.0L",
    "anio": "2001-2007",
    "filtro_aceite": { "marca": null, "sku": null },
    "filtro_aceite_sintetico": { "marca": null, "sku": null },
    "filtro_aceite_cartucho": { "marca": "Interfil", "sku": "OF-6744" },
    "filtro_aire": { "marca": "Interfil", "sku": "F-583A" },
    "filtro_gasolina": { "marca": "Interfil", "sku": "FGI-212A" },
    "filtro_cabina": { "marca": "Interfil", "sku": "CFI-93BW" }
  },
  {
    "modelo": "MONDEO",
    "motor": "2.5L V6",
    "anio": "2001-2007",
    "filtro_aceite": { "marca": "Interfil", "sku": "OF-2 / OF-6714" },
    "filtro_aceite_sintetico": { "marca": "Interfil", "sku": "OF-2STX" },
    "filtro_aceite_cartucho": { "marca": null, "sku": null },
    "filtro_aire": { "marca": "Interfil", "sku": "F-583A" },
    "filtro_gasolina": { "marca": "Interfil", "sku": "FGI-212A" },
    "filtro_cabina": { "marca": "Interfil", "sku": "CFI-93BW" }
  },
  {
    "modelo": "MONDEO",
    "motor": "3.0L V6",
    "anio": "2005-2007",
    "filtro_aceite": { "marca": "Interfil", "sku": "OF-2" },
    "filtro_aceite_sintetico": { "marca": "Interfil", "sku": "OF-2STX" },
    "filtro_aceite_cartucho": { "marca": null, "sku": null },
    "filtro_aire": { "marca": "Interfil", "sku": "F-583A" },
    "filtro_gasolina": { "marca": "Interfil", "sku": "FGI-212A" },
    "filtro_cabina": { "marca": "Interfil", "sku": "CFI-93BW" }
  }
]
